timelessnesses/typed_env.py
timelessnesses_typed_env-1.0.3.dist-info/LICENSE
timelessnesses_typed_env-1.0.3.dist-info/METADATA
timelessnesses_typed_env-1.0.3.dist-info/WHEEL
timelessnesses_typed_env-1.0.3.dist-info/RECORD
