Metadata-Version: 2.1
Name: timelessnesses-typed-env
Version: 1.0.3
Summary: A python module that help you have a type safety on enviroment variable
Home-page: https://github.com/timelessnesses/typed_env
License: MIT
Author: timelessnesses
Author-email: mooping3roblox@gmail.com
Requires-Python: >=3.8,<4.0
Classifier: License :: OSI Approved :: MIT License
Classifier: Programming Language :: Python :: 3
Classifier: Programming Language :: Python :: 3.8
Classifier: Programming Language :: Python :: 3.9
Classifier: Programming Language :: Python :: 3.10
Classifier: Programming Language :: Python :: 3.11
Requires-Dist: python-dotenv (>=1.0.0,<2.0.0)
